{"static":{"address":110636094.21276462,"date":1558165932172,"trait":0,"size":5420,"supply":9997},"stats":{"one_hour_volume":0.47,"six_hour_volume":0.47,"one_day_volume":5.1145,"seven_day_volume":19.0630999,"thirty_day_volume":103.27878489999996,"total_sales":24353,"num_owners":3977,"average_price":0.8914445478486831,"market_cap":6147.542248396774},"dynamic":{"ownerAddress":45187438.137722194,"ownerTransfers":2,"ownerTransactions":53,"gasSafe":17,"gasPorpose":18,"gasFast":19,"blockNo":7782949,"blockMiner":47233577.9494254,"blockReward":2065805321977406000},"transactionMin":{"blockNumber":7782722,"timeStamp":1558162935000,"nonce":0,"transactionIndex":0,"value":0,"gas":21000,"gasPrice":400000000,"cumulativeGasUsed":46214,"gasUsed":21000,"confirmations":571},"transactionMax":{"blockNumber":15834431,"timeStamp":1666813595000,"nonce":154526,"transactionIndex":698,"value":55338652530694570,"gas":5000000,"gasPrice":976022218431,"cumulativeGasUsed":30087537,"gasUsed":5000000,"confirmations":8052280}}